mycalc/calculator.py
yoonjin_calculator-0.0.1.dist-info/LICENSE
yoonjin_calculator-0.0.1.dist-info/METADATA
yoonjin_calculator-0.0.1.dist-info/WHEEL
yoonjin_calculator-0.0.1.dist-info/top_level.txt
yoonjin_calculator-0.0.1.dist-info/RECORD
