Metadata-Version: 2.1
Name: yoonjin-calculator
Version: 0.0.1
Summary: nice calculator
Author: yoonjin
License: UNKNOWN
Platform: UNKNOWN
License-File: LICENSE
